vec2tidb/__init__.py
vec2tidb/cli.py
vec2tidb/processing.py
vec2tidb/tidb.py
vec2tidb/commands/__init__.py
vec2tidb/commands/qdrant.py
vec2tidb-0.0.5.dist-info/METADATA
vec2tidb-0.0.5.dist-info/WHEEL
vec2tidb-0.0.5.dist-info/entry_points.txt
vec2tidb-0.0.5.dist-info/licenses/LICENSE
vec2tidb-0.0.5.dist-info/RECORD
