Metadata-Version: 2.4
Name: vec2tidb
Version: 0.0.5
Summary: A CLI tool for migrating data from third-party vector databases to TiDB
Author-email: Mini256 <minianter@foxmail.com>
License-File: LICENSE
Requires-Python: >=3.10
Requires-Dist: click>=8.0.0
Requires-Dist: dotenv>=0.9.9
Requires-Dist: parse>=1.20.2
Requires-Dist: pytest-cov>=6.2.1
Requires-Dist: pytidb>=0.0.9
Requires-Dist: qdrant-client>=1.10.1
Requires-Dist: tqdm>=4.66.0
Provides-Extra: dev
Requires-Dist: black>=24.4; extra == 'dev'
Requires-Dist: commitizen>=3.22.0; extra == 'dev'
Requires-Dist: flake8>=5.0.4; extra == 'dev'
Requires-Dist: isort>=5.10.1; extra == 'dev'
Requires-Dist: mkdocs-material>=9.5.31; extra == 'dev'
Requires-Dist: mkdocs>=1.6.0; extra == 'dev'
Requires-Dist: pre-commit>=3.5.0; extra == 'dev'
Requires-Dist: pytest-cov>=5.0.0; extra == 'dev'
Requires-Dist: pytest>=8.2.2; extra == 'dev'
Requires-Dist: python-dotenv>=1.0.1; extra == 'dev'
Requires-Dist: python-semantic-release>=9.4.2; extra == 'dev'
